{
  "status": "done",
  "assets": {
    "../css/style.css": {
      "name": "../css/style.css",
      "path": "E:\\OpenServer\\domains\\t-electroniks\\account\\static\\account\\css\\style.css"
    },
    "main-main-9b4e9a51fc1bf064dda3.js": {
      "name": "main-main-9b4e9a51fc1bf064dda3.js",
      "path": "E:\\OpenServer\\domains\\t-electroniks\\account\\static\\account\\javascripts\\main-main-9b4e9a51fc1bf064dda3.js"
    }
  },
  "chunks": {
    "main": [
      "../css/style.css",
      "main-main-9b4e9a51fc1bf064dda3.js"
    ]
  }
}